AUTHORS.md
CHANGES.md
LICENSE
MANIFEST.in
README.md
setup.py
Flask_Cake.egg-info/PKG-INFO
Flask_Cake.egg-info/SOURCES.txt
Flask_Cake.egg-info/dependency_links.txt
Flask_Cake.egg-info/not-zip-safe
Flask_Cake.egg-info/requires.txt
Flask_Cake.egg-info/top_level.txt
flask_cake/__init__.py
flask_cake/cake.py
flask_cake/tests/test_cake.py