Metadata-Version: 1.1
Name: Flask-Cake
Version: 0.3.1
Summary: Flask extension to execute Cake on filesystem events.
Home-page: http://github.com/rsenk330/Flask-Cake
Author: Ryan Senkbeil
Author-email: me@ryansenkbeil.com
License: BSD
Platform: any
Classifier: Environment :: Web Environment
Classifier: Intended Audience :: Developers
Classifier: License :: OSI Approved :: BSD License
Classifier: Operating System :: OS Independent
Classifier: Programming Language :: Python :: 2.7
Classifier: Programming Language :: Python :: 3.4
Classifier: Topic :: Internet :: WWW/HTTP :: Dynamic Content
Classifier: Topic :: Software Development :: Libraries :: Python Modules
